aqara_capi/__init__.py
aqara_capi/consts.py
aqara_capi/misc.py
aqara_capi/response.py
aqara_capi/client/__init__.py
aqara_capi/client/auth.py
aqara_capi/client/base.py
aqara_capi/client/client.py
aqara_capi/client/device.py
aqara_capi/client/position.py
aqara_capi/client/resource.py
aqara_capi-1.2.0.dist-info/LICENSE
aqara_capi-1.2.0.dist-info/METADATA
aqara_capi-1.2.0.dist-info/WHEEL
aqara_capi-1.2.0.dist-info/top_level.txt
aqara_capi-1.2.0.dist-info/RECORD
