Metadata-Version: 2.1
Name: aqara-capi
Version: 1.2.0
Summary: Aqara Cloud API SDK
Home-page: https://github.com/moff4/aqara_capi
Author: Komissarov Andrey
Author-email: Komissar.off.andrey@gmail.com
Classifier: Programming Language :: Python :: 3.10
Classifier: Programming Language :: Python :: 3.9
Classifier: Operating System :: OS Independent
License-File: LICENSE
Requires-Dist: requests (>=2.28.1)
Requires-Dist: pydantic (>=1.9.0)
